pysmoother/__init__.py
pysmoother-0.0.7.dist-info/METADATA
pysmoother-0.0.7.dist-info/WHEEL
pysmoother-0.0.7.dist-info/licenses/LICENSE
pysmoother-0.0.7.dist-info/RECORD
