Metadata-Version: 2.4
Name: pysmoother
Version: 0.0.7
Summary: Fit natural cubic polynomial splines, local regression and weighted smoothing splines to fit generalized additive models
Project-URL: Homepage, https://github.com/shashboy/pysmoother
Project-URL: Issues, https://github.com/shashboy/pysmoother
Author-email: Shashank Sharma <shashboy@gmail.com>
License-File: LICENSE
Classifier: License :: OSI Approved :: GNU General Public License v3 (GPLv3)
Classifier: Operating System :: OS Independent
Classifier: Programming Language :: Python :: 3
Requires-Python: >=3.0
